LibuvZhongwenJiaocheng/README.md
LibuvZhongwenJiaocheng/__init__.py
LibuvZhongwenJiaocheng/__main__.py
LibuvZhongwenJiaocheng/file.epub
LibuvZhongwenJiaocheng/index.html
LibuvZhongwenJiaocheng/css/__init__.py
LibuvZhongwenJiaocheng/css/annotations.css
LibuvZhongwenJiaocheng/css/main.css
LibuvZhongwenJiaocheng/css/normalize.css
LibuvZhongwenJiaocheng/css/popup.css
LibuvZhongwenJiaocheng/font/__init__.py
LibuvZhongwenJiaocheng/font/fontello.eot
LibuvZhongwenJiaocheng/font/fontello.svg
LibuvZhongwenJiaocheng/font/fontello.ttf
LibuvZhongwenJiaocheng/font/fontello.woff
LibuvZhongwenJiaocheng/img/__init__.py
LibuvZhongwenJiaocheng/img/annotator-glyph-sprite.png
LibuvZhongwenJiaocheng/img/annotator-icon-sprite.png
LibuvZhongwenJiaocheng/img/apple-touch-icon.png
LibuvZhongwenJiaocheng/img/cancelfullscreen.png
LibuvZhongwenJiaocheng/img/close.png
LibuvZhongwenJiaocheng/img/fullscreen.png
LibuvZhongwenJiaocheng/img/loader.gif
LibuvZhongwenJiaocheng/img/menu-icon.png
LibuvZhongwenJiaocheng/img/save.png
LibuvZhongwenJiaocheng/img/saved.png
LibuvZhongwenJiaocheng/img/settings-s.png
LibuvZhongwenJiaocheng/img/settings.png
LibuvZhongwenJiaocheng/img/star.png
LibuvZhongwenJiaocheng/js/__init__.py
LibuvZhongwenJiaocheng/js/epub.js
LibuvZhongwenJiaocheng/js/epub.min.js
LibuvZhongwenJiaocheng/js/epub.min.map
LibuvZhongwenJiaocheng/js/hooks.min.js
LibuvZhongwenJiaocheng/js/hooks.min.map
LibuvZhongwenJiaocheng/js/reader.js
LibuvZhongwenJiaocheng/js/reader.js.map
LibuvZhongwenJiaocheng/js/reader.min.js
LibuvZhongwenJiaocheng/js/reader.min.map
LibuvZhongwenJiaocheng/js/hooks/__init__.py
LibuvZhongwenJiaocheng/js/hooks/extensions/__init__.py
LibuvZhongwenJiaocheng/js/hooks/extensions/highlight.js
LibuvZhongwenJiaocheng/js/libs/__init__.py
LibuvZhongwenJiaocheng/js/libs/jquery.min.js
LibuvZhongwenJiaocheng/js/libs/localforage.min.js
LibuvZhongwenJiaocheng/js/libs/screenfull.js
LibuvZhongwenJiaocheng/js/libs/screenfull.min.js
LibuvZhongwenJiaocheng/js/libs/zip.min.js
libuv_zhongwen_jiaocheng-2024.3.2.0.dist-info/METADATA
libuv_zhongwen_jiaocheng-2024.3.2.0.dist-info/WHEEL
libuv_zhongwen_jiaocheng-2024.3.2.0.dist-info/entry_points.txt
libuv_zhongwen_jiaocheng-2024.3.2.0.dist-info/top_level.txt
libuv_zhongwen_jiaocheng-2024.3.2.0.dist-info/RECORD
